plassembler/__init__.py
plassembler/utils/CITATION
plassembler/utils/VERSION
plassembler/utils/assembly.py
plassembler/utils/bam.py
plassembler/utils/cleanup.py
plassembler/utils/concat.py
plassembler/utils/db.py
plassembler/utils/depth.py
plassembler/utils/external_tools.py
plassembler/utils/input_commands.py
plassembler/utils/mapping.py
plassembler/utils/no_assembly.py
plassembler/utils/plass_class.py
plassembler/utils/qc.py
plassembler/utils/run_canu.py
plassembler/utils/run_dnaapler.py
plassembler/utils/run_mash.py
plassembler/utils/run_unicycler.py
plassembler/utils/sam_to_fastq.py
plassembler/utils/test_incompatibility.py
plassembler/utils/util.py
plassembler-1.8.2.dist-info/METADATA
plassembler-1.8.2.dist-info/WHEEL
plassembler-1.8.2.dist-info/entry_points.txt
plassembler-1.8.2.dist-info/licenses/AUTHORS.md
plassembler-1.8.2.dist-info/licenses/LICENSE
plassembler-1.8.2.dist-info/RECORD
