Metadata-Version: 2.4
Name: plassembler
Version: 1.8.2
Summary: Quickly and accurately assemble plasmids in hybrid sequenced bacterial isolates
License: MIT
License-File: AUTHORS.md
License-File: LICENSE
Keywords: microbial,bioinformatics,plasmids,bacteria
Author: George Bouras
Author-email: george.bouras@adelaide.edu.au
Requires-Python: >=3.8,<3.14
Classifier: License :: OSI Approved :: MIT License
Classifier: Programming Language :: Python :: 3
Classifier: Programming Language :: Python :: 3.8
Classifier: Programming Language :: Python :: 3.9
Classifier: Programming Language :: Python :: 3.10
Classifier: Programming Language :: Python :: 3.11
Classifier: Programming Language :: Python :: 3.12
Classifier: Programming Language :: Python :: 3.13
Requires-Dist: alive-progress (>=3.0.1)
Requires-Dist: biopython (>=1.76)
Requires-Dist: click (>=8.0.0)
Requires-Dist: loguru (>=0.5.3)
Requires-Dist: pandas (>=1.4.2)
Requires-Dist: pysam (>=0.16.0)
Requires-Dist: pyyaml (>=6.0)
Requires-Dist: requests (>=2.25.1)
Project-URL: Homepage, https://github.com/gbouras13/plassembler
Project-URL: Repository, https://github.com/gbouras13/plassembler
